<?xml version="1.0" encoding="UTF-8"?>
<objects serializationModel="Studio.02.02.00">
	<object class="AudioFile" id="{a031f352-f4b5-4acb-8d75-9884588325e0}">
		<property name="assetPath">
			<value>Final Lap Sound.wav</value>
		</property>
		<property name="isStreaming">
			<value>true</value>
		</property>
		<property name="frequencyInKHz">
			<value>48</value>
		</property>
		<property name="channelCount">
			<value>2</value>
		</property>
		<property name="length">
			<value>10.285708333333334</value>
		</property>
		<relationship name="masterAssetFolder">
			<destination>{b3cd06a2-59cd-4311-9765-4069007cb72d}</destination>
		</relationship>
	</object>
</objects>
